{"data":{"markdownRemark":{"html":"<p>For anyone who wondering why I didn’t online for about 2 weeks: I’m busy. <br>\nIt’s more than likely I’ll be rarely online until next saga comes.<br>\nIn the mean times currently I’m trying out about how to import my ECO char into MMD so that I can do *many* things on it. The progress is going smoothly, though sadly due to my schedule I can’t do this project all day long. I already able to take the mess, texture, and implement the bone. All that’s left is integrate it into PMD/MMD (for some obvious reason, it still can’t move in PMD)</p>\n<div style=\"clear: both;text-align: center\">\n  <a href=\"http://hourai.etealune.net/wp-content/uploads/2012/02/day3.png\" style=\"margin-left: 1em;margin-right: 1em\"><img border=\"0\" height=\"356\" src=\"http://hourai.etealune.net/wp-content/uploads/2012/02/day3-300x168.png\" width=\"640\"></a>\n</div>\n<div style=\"text-align: center\">\n  <span style=\"font-size: x-small\">The bread and eyes isn&#8217;t implemented yet&#8230;. well, let that slide.</span>\n</div>","frontmatter":{"title":"Busy…"}}},"pageContext":{"isCreatedByStatefulCreatePages":false,"slug":"/2012-02-17-busy/"}}